{
  "$schema": "https://schema.management.azure.com/schemas/2019-04-01/deploymentParameters.json#",
  "contentVersion": "1.0.0.0",
  "parameters": {
    "location": {
      "value": "eastus"
    },
    "sqlServerName": {
      "value": "dphealth-sql-UNIQUE"
    },
    "sqlDatabaseSku": {
      "value": "S0"
    },
    "storageAccountName": {
      "value": "dphealthstgUNIQUE"
    },
    "dataFactoryName": {
      "value": "dphealth-adf-UNIQUE"
    },
    "logAnalyticsWorkspaceName": {
      "value": ""
    },
    "sqlAdministratorLogin": {
      "value": "sqladmin"
    },
    "sqlAdministratorLoginPassword": {
      "value": "CHANGE_ME_STRONG_PASSWORD"
    },
    "enableSqlPublicNetworkAccess": {
      "value": true
    },
    "tags": {
      "value": {
        "Environment": "Dev",
        "Project": "DataPlatformHealth",
        "ManagedBy": "Bicep"
      }
    }
  }
}

